krecommend/__init__.py
krecommend/recommend.py
krecommend-0.0.2.dist-info/LICENSE
krecommend-0.0.2.dist-info/METADATA
krecommend-0.0.2.dist-info/WHEEL
krecommend-0.0.2.dist-info/top_level.txt
krecommend-0.0.2.dist-info/RECORD
