Metadata-Version: 2.1
Name: krecommend
Version: 0.0.2
Summary: A Python library for easily building  recommender systems for SQLAlchemy tables and pandas dataframe
Home-page: https://github.com/saheedniyi02/KRecommend
Author: Saheed Azeez
Author-email: saheedniyi02@gmail.com
License: MIT
Keywords: Data Science,machine learning,web development,software development,sql,pandas
Classifier: Programming Language :: Python :: 3
Classifier: License :: OSI Approved :: MIT License
Classifier: Intended Audience :: Science/Research
Classifier: Intended Audience :: Developers
Classifier: Programming Language :: Python
Classifier: Topic :: Software Development
Classifier: Operating System :: OS Independent
Classifier: Operating System :: Microsoft :: Windows
Classifier: Operating System :: POSIX
Classifier: Operating System :: Unix
Classifier: Operating System :: MacOS
License-File: LICENSE
Requires-Dist: pandas
Requires-Dist: sqlalchemy
Requires-Dist: numpy
Requires-Dist: scikit-learn
